{"C:\\Users\\parit\\OneDrive\\Documents\\Desktop\\ATS-Project\\ATS-Resume\\.agents\\skills\\react-router\\SKILL.md":{"size":6104,"mtime_ns":1784276999285721300,"word_count":588,"hashes":{".agents/skills/react-router/skill.md":"ba177217bb54d968a0eae4a2d738b70f8e805136f51431bfaddf9f99f594fcb5"}},"C:\\Users\\parit\\OneDrive\\Documents\\Desktop\\ATS-Project\\ATS-Resume\\.agents\\skills\\react-router\\references\\data-mode.md":{"size":4797,"mtime_ns":1784276999270643200,"word_count":588,"hashes":{".agents/skills/react-router/references/data-mode.md":"723737535446a898f93141b990a0cdb1de0844c98c26e2bf8afec3e2634ef4f3"}},"C:\\Users\\parit\\OneDrive\\Documents\\Desktop\\ATS-Project\\ATS-Resume\\.agents\\skills\\react-router\\references\\declarative-mode.md":{"size":3284,"mtime_ns":1784276999281947000,"word_count":422,"hashes":{".agents/skills/react-router/references/declarative-mode.md":"047de0644af19a07b05ac63211e475399703f4fd7304c4660a1f26621de54ee4"}},"C:\\Users\\parit\\OneDrive\\Documents\\Desktop\\ATS-Project\\ATS-Resume\\.agents\\skills\\react-router\\references\\framework-mode.md":{"size":7271,"mtime_ns":1784276999285721300,"word_count":807,"hashes":{".agents/skills/react-router/references/framework-mode.md":"d2eb61cb80b1e9d974955ae8a36ba6f5428fc09d262f58f4a085b2fe61e27a19"}},"C:\\Users\\parit\\OneDrive\\Documents\\Desktop\\ATS-Project\\ATS-Resume\\.agents\\skills\\react-router\\references\\rsc.md":{"size":3447,"mtime_ns":1784276999285721300,"word_count":481,"hashes":{".agents/skills/react-router/references/rsc.md":"1ade30150b77579972af425243a055e7d7d091601481acfd1b62b6995e7209ae"}},"C:\\Users\\parit\\OneDrive\\Documents\\Desktop\\ATS-Project\\ATS-Resume\\README.md":{"size":1839,"mtime_ns":1781728720000000000,"word_count":245,"hashes":{"readme.md":"3cdfa8a4e7e0caa90a3134617494ee18fb7a817d43dbe40ebe6346e9eea4dbb0"}},"C:\\Users\\parit\\OneDrive\\Documents\\Desktop\\ATS-Project\\ATS-Resume\\app\\components\\ATS.tsx":{"size":3540,"mtime_ns":1784463253394241200,"word_count":286},"C:\\Users\\parit\\OneDrive\\Documents\\Desktop\\ATS-Project\\ATS-Resume\\app\\components\\Details.tsx":{"size":5728,"mtime_ns":1784463291776480700,"word_count":428},"C:\\Users\\parit\\OneDrive\\Documents\\Desktop\\ATS-Project\\ATS-Resume\\app\\components\\FileUploader.tsx":{"size":3429,"mtime_ns":1784446450487619100,"word_count":304},"C:\\Users\\parit\\OneDrive\\Documents\\Desktop\\ATS-Project\\ATS-Resume\\app\\components\\Navbar.tsx":{"size":854,"mtime_ns":1784446679380947000,"word_count":78},"C:\\Users\\parit\\OneDrive\\Documents\\Desktop\\ATS-Project\\ATS-Resume\\app\\components\\ResumeCard.tsx":{"size":2966,"mtime_ns":1784449428677345400,"word_count":262},"C:\\Users\\parit\\OneDrive\\Documents\\Desktop\\ATS-Project\\ATS-Resume\\app\\components\\ScoreCircle.tsx":{"size":1820,"mtime_ns":1784446442338392400,"word_count":160},"C:\\Users\\parit\\OneDrive\\Documents\\Desktop\\ATS-Project\\ATS-Resume\\app\\components\\Summary.tsx":{"size":2593,"mtime_ns":1784463242982058700,"word_count":237},"C:\\Users\\parit\\OneDrive\\Documents\\Desktop\\ATS-Project\\ATS-Resume\\app\\lib\\pdf.ts":{"size":1231,"mtime_ns":1784293835866057000,"word_count":131},"C:\\Users\\parit\\OneDrive\\Documents\\Desktop\\ATS-Project\\ATS-Resume\\app\\lib\\pdf2img.ts":{"size":2003,"mtime_ns":1784449343276302900,"word_count":210},"C:\\Users\\parit\\OneDrive\\Documents\\Desktop\\ATS-Project\\ATS-Resume\\app\\lib\\puter.ts":{"size":1609,"mtime_ns":1784449831845842100,"word_count":188},"C:\\Users\\parit\\OneDrive\\Documents\\Desktop\\ATS-Project\\ATS-Resume\\app\\lib\\store.ts":{"size":603,"mtime_ns":1784463314838349300,"word_count":72},"C:\\Users\\parit\\OneDrive\\Documents\\Desktop\\ATS-Project\\ATS-Resume\\app\\lib\\util.ts":{"size":307,"mtime_ns":1784444802785024200,"word_count":39},"C:\\Users\\parit\\OneDrive\\Documents\\Desktop\\ATS-Project\\ATS-Resume\\app\\lib\\utils.ts":{"size":239,"mtime_ns":1784449330979613800,"word_count":23},"C:\\Users\\parit\\OneDrive\\Documents\\Desktop\\ATS-Project\\ATS-Resume\\app\\root.tsx":{"size":1931,"mtime_ns":1784293861772860000,"word_count":200},"C:\\Users\\parit\\OneDrive\\Documents\\Desktop\\ATS-Project\\ATS-Resume\\app\\routes.ts":{"size":243,"mtime_ns":1784463201732186900,"word_count":20},"C:\\Users\\parit\\OneDrive\\Documents\\Desktop\\ATS-Project\\ATS-Resume\\app\\routes\\ResumeDetails.tsx":{"size":9152,"mtime_ns":1784465570965997500,"word_count":867},"C:\\Users\\parit\\OneDrive\\Documents\\Desktop\\ATS-Project\\ATS-Resume\\app\\routes\\UploadResume.tsx":{"size":12445,"mtime_ns":1784449417082853800,"word_count":1046},"C:\\Users\\parit\\OneDrive\\Documents\\Desktop\\ATS-Project\\ATS-Resume\\app\\routes\\home.tsx":{"size":10602,"mtime_ns":1784467316267328800,"word_count":974},"C:\\Users\\parit\\OneDrive\\Documents\\Desktop\\ATS-Project\\ATS-Resume\\constants\\index.ts":{"size":4191,"mtime_ns":1784286344239952500,"word_count":495},"C:\\Users\\parit\\OneDrive\\Documents\\Desktop\\ATS-Project\\ATS-Resume\\package.json":{"size":817,"mtime_ns":1784442583015126200,"word_count":65,"hashes":{"package.json":"9f5ae69200e5ee6ef50e0e6ba7f5cc86a3c149cd53c6529a27fe6db9c1662dc3"}},"C:\\Users\\parit\\OneDrive\\Documents\\Desktop\\ATS-Project\\ATS-Resume\\public\\icons\\ats-bad.svg":{"size":6333,"mtime_ns":1784281020646875600,"word_count":646,"hashes":{"public/icons/ats-bad.svg":"2dc30ecbc0ca75100c0257058c72e607eb206cf159c151264e8c78519df4a0cc"}},"C:\\Users\\parit\\OneDrive\\Documents\\Desktop\\ATS-Project\\ATS-Resume\\public\\icons\\ats-good.svg":{"size":6359,"mtime_ns":1784281020660942400,"word_count":640,"hashes":{"public/icons/ats-good.svg":"8d03e1e6c256d64da24e252c53673cc68d3df1c4848397905c18c27e4b744578"}},"C:\\Users\\parit\\OneDrive\\Documents\\Desktop\\ATS-Project\\ATS-Resume\\public\\icons\\ats-warning.svg":{"size":7005,"mtime_ns":1784281020675740500,"word_count":715,"hashes":{"public/icons/ats-warning.svg":"a9b6b6dcbe5c7d5132bf4e92b83d7f191212905a62447248099c067c3764ab05"}},"C:\\Users\\parit\\OneDrive\\Documents\\Desktop\\ATS-Project\\ATS-Resume\\public\\icons\\back.svg":{"size":280,"mtime_ns":1784281020685105100,"word_count":20,"hashes":{"public/icons/back.svg":"66b3a0f2ace706b1412b676668d67a9232e51340305e8f64bdaf692b3ae8beab"}},"C:\\Users\\parit\\OneDrive\\Documents\\Desktop\\ATS-Project\\ATS-Resume\\public\\icons\\check.svg":{"size":454,"mtime_ns":1784281020702951100,"word_count":40,"hashes":{"public/icons/check.svg":"ebe0a55e994ff57974ace55d88d1a4e52ba240cc24d3409d2e880c45e0b72966"}},"C:\\Users\\parit\\OneDrive\\Documents\\Desktop\\ATS-Project\\ATS-Resume\\public\\icons\\cross.svg":{"size":839,"mtime_ns":1784281020710460300,"word_count":48,"hashes":{"public/icons/cross.svg":"08730cb51af864b0f994ffe4dd3cd772c8053d2bc866933a43147219e95780f5"}},"C:\\Users\\parit\\OneDrive\\Documents\\Desktop\\ATS-Project\\ATS-Resume\\public\\icons\\info.svg":{"size":7111,"mtime_ns":1784281020710460300,"word_count":710,"hashes":{"public/icons/info.svg":"3f6c82006c097aa6fa6ce4290920e0c05e1cac3c9216cf57d543164206a297e1"}},"C:\\Users\\parit\\OneDrive\\Documents\\Desktop\\ATS-Project\\ATS-Resume\\public\\icons\\pin.svg":{"size":385,"mtime_ns":1784281020726414300,"word_count":47,"hashes":{"public/icons/pin.svg":"b811eb00199fabbe76d2d992b85fa13be77d8fc00de4d8557af92d96c90e6d0c"}},"C:\\Users\\parit\\OneDrive\\Documents\\Desktop\\ATS-Project\\ATS-Resume\\public\\icons\\warning.svg":{"size":900,"mtime_ns":1784281020742326200,"word_count":83,"hashes":{"public/icons/warning.svg":"7e2fd451d103bc88654cccdafb91ec41236b7a7dd86763d0aee4c730509ed26b"}},"C:\\Users\\parit\\OneDrive\\Documents\\Desktop\\ATS-Project\\ATS-Resume\\public\\images\\bg-auth.svg":{"size":7119,"mtime_ns":1784281020758296400,"word_count":518,"hashes":{"public/images/bg-auth.svg":"c12e9f57da98a0afe9158eb5f33e14238b4d21e26e001f62deb5b2226a60e3cf"}},"C:\\Users\\parit\\OneDrive\\Documents\\Desktop\\ATS-Project\\ATS-Resume\\public\\images\\bg-main.svg":{"size":6872,"mtime_ns":1784281020765954400,"word_count":446,"hashes":{"public/images/bg-main.svg":"e0173f883ffb550426ce7d001f54c4bb16bda469dc907e90de960b88aebbc898"}},"C:\\Users\\parit\\OneDrive\\Documents\\Desktop\\ATS-Project\\ATS-Resume\\public\\images\\bg-small.svg":{"size":5655,"mtime_ns":1784281020774060400,"word_count":368,"hashes":{"public/images/bg-small.svg":"29a5621e2bc98f0d31d9d6e0492881df8e2385342d2aeefe35055ee3f34817bf"}},"C:\\Users\\parit\\OneDrive\\Documents\\Desktop\\ATS-Project\\ATS-Resume\\public\\images\\logo.svg":{"size":6019,"mtime_ns":1781780828588913100,"word_count":636,"hashes":{"public/images/logo.svg":"a8a2d789212d93605d91c367cb873e47661da8b49e24306c950717217f62068c"}},"C:\\Users\\parit\\OneDrive\\Documents\\Desktop\\ATS-Project\\ATS-Resume\\public\\images\\pdf.png":{"size":8183,"mtime_ns":1784281020774060400,"word_count":301,"hashes":{"public/images/pdf.png":"b80b7e3417bc029bca566fa181ea416fffcd8cfd51239edf3bcfe2d3b0da935c"}},"C:\\Users\\parit\\OneDrive\\Documents\\Desktop\\ATS-Project\\ATS-Resume\\public\\images\\resume-scan-2.gif":{"size":616213,"mtime_ns":1784281020806006300,"word_count":23748,"hashes":{"public/images/resume-scan-2.gif":"c5e2d31825818f876a1e5dec314f6c4172c903ccbcbd920722df15472adbcf74"}},"C:\\Users\\parit\\OneDrive\\Documents\\Desktop\\ATS-Project\\ATS-Resume\\public\\images\\resume-scan.gif":{"size":1380401,"mtime_ns":1784281020821935500,"word_count":43091,"hashes":{"public/images/resume-scan.gif":"a2f43a77e8e36ebf77ed1be7ceb420a8415893b9f52739706e27937ae3f0dc7e"}},"C:\\Users\\parit\\OneDrive\\Documents\\Desktop\\ATS-Project\\ATS-Resume\\public\\images\\resume_01.png":{"size":390523,"mtime_ns":1784281020837988800,"word_count":14004,"hashes":{"public/images/resume_01.png":"3393394da1f763380026e11110de5ff2a299a3b1c334cbb42ffbb051b093a8f3"}},"C:\\Users\\parit\\OneDrive\\Documents\\Desktop\\ATS-Project\\ATS-Resume\\public\\images\\resume_02.png":{"size":1240560,"mtime_ns":1784281020875106600,"word_count":45741,"hashes":{"public/images/resume_02.png":"2733944e295fd4171bc40afbf95ff7275d0abf1c78af6ac1b0fb4060584d5c72"}},"C:\\Users\\parit\\OneDrive\\Documents\\Desktop\\ATS-Project\\ATS-Resume\\public\\images\\resume_03.png":{"size":378242,"mtime_ns":1784281020885717700,"word_count":12927,"hashes":{"public/images/resume_03.png":"57618e5eb356473f2be8b910fd40ef2ebddb7c84b9b1fe45109224c9fc6e0ff4"}},"C:\\Users\\parit\\OneDrive\\Documents\\Desktop\\ATS-Project\\ATS-Resume\\public\\pdf.worker.min.mjs":{"size":1035022,"mtime_ns":1784281020623050600,"word_count":18174},"C:\\Users\\parit\\OneDrive\\Documents\\Desktop\\ATS-Project\\ATS-Resume\\react-router.config.ts":{"size":205,"mtime_ns":1781728720000000000,"word_count":31},"C:\\Users\\parit\\OneDrive\\Documents\\Desktop\\ATS-Project\\ATS-Resume\\tsconfig.json":{"size":585,"mtime_ns":1781728720000000000,"word_count":47,"hashes":{"tsconfig.json":"06d6ca650c99f21ff0a6fd3bfd082bb751d32467e8a906bced496e8503924a76"}},"C:\\Users\\parit\\OneDrive\\Documents\\Desktop\\ATS-Project\\ATS-Resume\\types\\index.d.ts":{"size":1011,"mtime_ns":1784282529463522700,"word_count":112},"C:\\Users\\parit\\OneDrive\\Documents\\Desktop\\ATS-Project\\ATS-Resume\\types\\puter.d.ts":{"size":92,"mtime_ns":1784293821999666400,"word_count":15},"C:\\Users\\parit\\OneDrive\\Documents\\Desktop\\ATS-Project\\ATS-Resume\\vite.config.ts":{"size":257,"mtime_ns":1781728720000000000,"word_count":28}}